raincloudpy/__init__.py
raincloudpy/raincloud.py
raincloudpy-0.4.6.dist-info/licenses/LICENSE
tests/__init__.py
tests/test_raincloud.py
raincloudpy-0.4.6.dist-info/METADATA
raincloudpy-0.4.6.dist-info/WHEEL
raincloudpy-0.4.6.dist-info/top_level.txt
raincloudpy-0.4.6.dist-info/RECORD
