Metadata-Version: 2.4
Name: raincloudpy
Version: 0.4.6
Summary: Beautiful raincloud plots for Python
Home-page: https://github.com/bsgarcia/raincloudpy
Author: bsgarcia
Author-email: bsgarcia <basilegarcia@gmail.com>
License: MIT
Project-URL: Homepage, https://github.com/bsgarcia/raincloudpy
Project-URL: Documentation, https://github.com/bsgarcia/raincloudpy#readme
Project-URL: Repository, https://github.com/bsgarcia/raincloudpy
Project-URL: Bug Reports, https://github.com/bsgarcia/raincloudpy/issues
Keywords: visualization,raincloud,plots,statistics,data-science
Classifier: Development Status :: 4 - Beta
Classifier: Intended Audience :: Science/Research
Classifier: Topic :: Scientific/Engineering :: Visualization
Classifier: License :: OSI Approved :: MIT License
Classifier: Programming Language :: Python :: 3
Classifier: Programming Language :: Python :: 3.7
Classifier: Programming Language :: Python :: 3.8
Classifier: Programming Language :: Python :: 3.9
Classifier: Programming Language :: Python :: 3.10
Classifier: Programming Language :: Python :: 3.11
Classifier: Programming Language :: Python :: 3.12
Requires-Python: >=3.7
License-File: LICENSE
Requires-Dist: numpy>=1.19.0
Requires-Dist: matplotlib>=3.3.0
Requires-Dist: scipy>=1.5.0
Requires-Dist: pandas>=1.1.0
Requires-Dist: seaborn>=0.11.0
Provides-Extra: dev
Requires-Dist: pytest>=6.0; extra == "dev"
Requires-Dist: pytest-cov>=2.0; extra == "dev"
Requires-Dist: black>=22.0; extra == "dev"
Requires-Dist: flake8>=3.9; extra == "dev"
Requires-Dist: mypy>=0.9; extra == "dev"
Dynamic: author
Dynamic: home-page
Dynamic: license-file
Dynamic: requires-python
